{
  "name": "LookupSnapshot",
  "description": "Run lookups on two different snapshots.",
  "serverSpecificationFile": "localhost.json",
  "billingAccount": "00708C-45D19D-27AAFA",
  "numberToRunInParallel": 3,
  "kubernetes": {
    "numberOfInitialPods" : 2
  },
  "application": {},
  "testScripts": [
    {
      "name": "RetrieveSnapshot",
      "totalNumberToRun": 1,
      "expectedSecondsForEach": 20
    },
    {
      "name": "RetrieveSnapshot",
      "totalNumberToRun": 15,
      "expectedSecondsForEach": 20
    }
  ],
  "testUserFiles": ["dumbledore.json", "voldemort.json"]
}
